finitelycomputable/idtrust_db/__init__.py
finitelycomputable/idtrust_db/controller.py
finitelycomputable/idtrust_db/helpers_for_tests.py
finitelycomputable/idtrust_db/models.py
finitelycomputable_idtrust_db_peewee-25.7.dist-info/METADATA
finitelycomputable_idtrust_db_peewee-25.7.dist-info/WHEEL
finitelycomputable_idtrust_db_peewee-25.7.dist-info/top_level.txt
finitelycomputable_idtrust_db_peewee-25.7.dist-info/RECORD
