Metadata-Version: 2.4
Name: finitelycomputable-idtrust-db-peewee
Version: 25.7
Summary: Peewee implementation of database layer for the Identification of Trust microsite
Author-email: Samuel Newbold <sam@rwsh.org>
License-Expression: AGPL-3.0-only
Project-URL: Documentation, https://github.com/thrasymache/microsites
Project-URL: Source, https://github.com/thrasymache/microsites
Project-URL: Gitlab, https://gitlab.com/thrasymache/microsites
Project-URL: sourcehut, https://git.sr.ht/~thrasymache/finitelycomputable-microsites
Project-URL: NotABug, https://notabug.org/thrasymache/finitelycomputable-microsites
Classifier: Development Status :: 3 - Alpha
Classifier: Environment :: Web Environment
Classifier: Intended Audience :: Developers
Classifier: Operating System :: OS Independent
Classifier: Programming Language :: Python
Classifier: Programming Language :: Python :: 3
Classifier: Programming Language :: Python :: 3.8
Classifier: Programming Language :: Python :: 3.9
Classifier: Programming Language :: Python :: 3.10
Classifier: Programming Language :: Python :: 3.11
Classifier: Topic :: Internet :: WWW/HTTP
Classifier: Topic :: Internet :: WWW/HTTP :: Dynamic Content
Requires-Python: >=3.8
Requires-Dist: peewee~=3.18
Provides-Extra: tests
Requires-Dist: pytest; extra == "tests"
Requires-Dist: pytest-env; extra == "tests"
Requires-Dist: finitelycomputable-tests; extra == "tests"
